pyaddin/__init__.py
pyaddin/addin.py
pyaddin/main.py
pyaddin/share.py
pyaddin/resources/CustomUI.xml
pyaddin/resources/main.cfg
pyaddin/resources/main.py
pyaddin/resources/scripts/__init__.py
pyaddin/resources/scripts/sample.py
pyaddin/resources/scripts/utils/__init__.py
pyaddin/resources/scripts/utils/context.py
pyaddin/resources/vba/UserRibbon.bas
pyaddin/resources/vba/general.bas
pyaddin/resources/vba/ribbon.bas
pyaddin/resources/xlam/[Content_Types].xml
pyaddin/resources/xlam/_rels/.rels
pyaddin/resources/xlam/docProps/app.xml
pyaddin/resources/xlam/docProps/core.xml
pyaddin/resources/xlam/xl/styles.xml
pyaddin/resources/xlam/xl/vbaProject.bin
pyaddin/resources/xlam/xl/workbook.xml
pyaddin/resources/xlam/xl/_rels/workbook.xml.rels
pyaddin/resources/xlam/xl/printerSettings/printerSettings1.bin
pyaddin/resources/xlam/xl/theme/theme1.xml
pyaddin/resources/xlam/xl/worksheets/sheet1.xml
pyaddin/resources/xlam/xl/worksheets/_rels/sheet1.xml.rels
pyaddin/xlam/__init__.py
pyaddin/xlam/ui.py
pyaddin/xlam/vba.py
pyAddin-0.1.0.dist-info/LICENSE
pyAddin-0.1.0.dist-info/METADATA
pyAddin-0.1.0.dist-info/WHEEL
pyAddin-0.1.0.dist-info/entry_points.txt
pyAddin-0.1.0.dist-info/top_level.txt
pyAddin-0.1.0.dist-info/RECORD
